cenv/__init__.py
cenv/cli.py
cenv/config.py
cenv/core.py
cenv/exceptions.py
cenv/github.py
cenv/logging_config.py
cenv/path_portability.py
cenv/platform_utils.py
cenv/process.py
cenv/publish.py
cenv/validation.py
claude_env-0.3.0.dist-info/METADATA
claude_env-0.3.0.dist-info/WHEEL
claude_env-0.3.0.dist-info/entry_points.txt
claude_env-0.3.0.dist-info/licenses/LICENSE
claude_env-0.3.0.dist-info/RECORD
