Metadata-Version: 2.4
Name: claude-env
Version: 0.3.0
Summary: Claude environment manager - switch between Claude Code configurations
Project-URL: Homepage, https://github.com/vtemian/claude-env
Project-URL: Documentation, https://github.com/vtemian/claude-env#readme
Project-URL: Repository, https://github.com/vtemian/claude-env
Project-URL: Bug Tracker, https://github.com/vtemian/claude-env/issues
Project-URL: Changelog, https://github.com/vtemian/claude-env/blob/main/CHANGELOG.md
Author-email: cenv contributors <contributors@cenv.io>
License: MIT
License-File: LICENSE
Keywords: claude,cli,configuration,devtools,environment
Classifier: Development Status :: 4 - Beta
Classifier: Intended Audience :: Developers
Classifier: License :: OSI Approved :: MIT License
Classifier: Operating System :: MacOS
Classifier: Operating System :: POSIX
Classifier: Programming Language :: Python :: 3
Classifier: Programming Language :: Python :: 3.10
Classifier: Programming Language :: Python :: 3.11
Classifier: Programming Language :: Python :: 3.12
Classifier: Topic :: Software Development
Classifier: Topic :: System :: Installation/Setup
Requires-Python: >=3.10
Requires-Dist: psutil<6.0.0,>=5.9.0
Requires-Dist: typer<1.0.0,>=0.9.0
Provides-Extra: dev
Requires-Dist: mypy>=1.7.0; extra == 'dev'
Requires-Dist: pytest-cov>=4.1.0; extra == 'dev'
Requires-Dist: pytest>=7.4.0; extra == 'dev'
Requires-Dist: ruff>=0.1.0; extra == 'dev'
Requires-Dist: types-psutil>=5.9.0; extra == 'dev'
